MANIFEST.in
README.txt
setup.cfg
setup.py
adi/__init__.py
adi.playlist.egg-info/PKG-INFO
adi.playlist.egg-info/SOURCES.txt
adi.playlist.egg-info/dependency_links.txt
adi.playlist.egg-info/entry_points.txt
adi.playlist.egg-info/namespace_packages.txt
adi.playlist.egg-info/not-zip-safe
adi.playlist.egg-info/requires.txt
adi.playlist.egg-info/top_level.txt
adi/playlist/__init__.py
adi/playlist/configure.zcml
adi/playlist/tests.py
adi/playlist/browser/.adi_playlist_view.pt.swp
adi/playlist/browser/__init__.py
adi/playlist/browser/adi_playlist_view.pt
adi/playlist/browser/configure.zcml
adi/playlist/browser/interfaces.py
adi/playlist/browser/resources/adi_playlist.css
adi/playlist/browser/resources/adi_playlist.js
adi/playlist/profiles/default/browserlayer.xml
adi/playlist/profiles/default/cssregistry.xml
adi/playlist/profiles/default/jsregistry.xml
adi/playlist/profiles/default/metadata.xml
adi/playlist/profiles/default/types/Folder.xml
docs/HISTORY.txt
docs/INSTALL.txt
docs/LICENSE.GPL
docs/LICENSE.txt