Metadata-Version: 1.1
Name: adi.playlist
Version: 0.3
Summary: Create a playlist in a folder filled with audio-files, using HTML5's audio-tag.
Home-page: https://github.com/ida/adi.playlist
Author: Ida Ebkes
Author-email: contact@ida-ebkes.eu
License: GPL
Platform: UNKNOWN
Classifier: Framework :: Plone
Classifier: Programming Language :: Python
